meseex/__init__.py
meseex/gather.py
meseex/meseex_box.py
meseex/meseex_store.py
meseex/mr_meseex.py
meseex/progress_bar.py
meseex/signals.py
meseex/utils.py
meseex/control_flow/__init__.py
meseex/control_flow/polling.py
meseex/control_flow/signals.py
meseex/tasks/__init__.py
meseex/tasks/async_task_executor.py
meseex/tasks/i_task_executor.py
meseex/tasks/task_executor.py
meseex/tasks/task_result.py
meseex/tasks/thread_pool_task_executor.py
meseex-0.0.5.dist-info/licenses/LICENSE
meseex-0.0.5.dist-info/METADATA
meseex-0.0.5.dist-info/WHEEL
meseex-0.0.5.dist-info/top_level.txt
meseex-0.0.5.dist-info/RECORD
