Metadata-Version: 2.4
Name: meseex
Version: 0.0.5
Author: SocAIty
License:                     GNU GENERAL PUBLIC LICENSE
Project-URL: Repository, https://github.com/SocAIty/meseex
Project-URL: Homepage, https://www.socaity.ai
Requires-Python: >=3.8
License-File: LICENSE
Requires-Dist: rich>=14.0.0
Requires-Dist: pydantic>=2.10.4
Dynamic: license-file
